Workbook

Sheet 453 Prompts
A1: 453 Cleaned PTE Write Essay Prompts (3-Model Verified)
A2: Each prompt is verified by 3 Local LLMs (Gemma 4, Qwen 3, DeepSeek-R1) with single task type and up to 3 topic tags.
A4: No. | B4: Cleaned PTE-style prompt | C4: Task type | D4: Primary topic | E4: Secondary topic 1 | F4: Secondary topic 2
A5: 1 | B5: “The only thing that interferes with my learning is education.” – Albert Einstein. What did he mean by that? Do you think he is correct? | C5: To what extent do you agree or disagree | D5: Education
A6: 2 | B6: A healthy diet is more effective for keeping fit than exercise. What is your opinion? | C6: To what extent do you agree or disagree | D6: Food and health
A7: 3 | B7: A healthy diet is more important for keeping fit than exercise. To what extent do you agree with this statement? Give an example or personal experiences. | C7: To what extent do you agree or disagree | D7: Food and health
A8: 4 | B8: Advertisements make people purchase things they don’t need or cannot afford, but they also convey information to increase people's life quality. What is your opinion? | C8: To what extent do you agree or disagree | D8: Media and communication
A9: 5 | B9: As cities expand, governments should look forward to creating better networks of public transport available for everyone rather than building more roads for vehicle owning population. To what extent do you agree or disagree? | C9: To what extent do you agree or disagree | D9: City development | E9: Government, politics, and diplomacy | F9: City development
A10: 6 | B10: As national services, which one deserves to receive more financial support, education or health? | C10: others | D10: Government, politics, and diplomacy | E10: Food and health | F10: Economy, money, and trade
A11: 7 | B11: Because university degrees can get people jobs with higher salaries, university students should pay full cost for their education. Do you agree or not? | C11: To what extent do you agree or disagree | D11: Education | E11: Economy, money, and trade
A12: 8 | B12: Some people believe that all cities and towns should have at least one large public open space. To what extent do you agree or disagree? | C12: To what extent do you agree or disagree | D12: City development | E12: Environment | F12: Lifestyle
A13: 9 | B13: Climate change is a concerning global issue. Who has the main responsibility to take action to solve this problem, governments, large companies, or individuals? | C13: others | D13: Climate | E13: Environment
A14: 10 | B14: Communication has changed significantly in the last 10 years. Discuss the positive and negative impacts of this change. | C14: others | D14: Media and communication
A15: 11 | B15: Culture shock is a new worry leading to less immigration. What are the possible options to eradicate this issue? | C15: others | D15: Socio-cultural and global issues
A16: 12 | B16: Some people work long hours to achieve success, but others feel that we should spend more free time for fun than for money. Which lifestyle do you prefer? Explain your opinion. | C16: others | D16: Lifestyle | E16: Leisure, sports, and hobbies | F16: Work
A17: 13 | B17: Do you believe that the industrial revolution was the main factor for problems in developed nations? | C17: To what extent do you agree or disagree | D17: Economy, money, and trade
A18: 14 | B18: Do you think consumers should avoid over-packaged products or is it the responsibility of manufacturers to avoid extra packaging? Give your views or any relevant examples based on your own experience. | C18: others | D18: Environment
A19: 15 | B19: Do you think it has a positive or negative impact on you if you buy a home close to the workplace? | C19: Is it a positive or negative development | D19: Lifestyle
A20: 16 | B20: For children, using films to study is as important as studying literature. To what extent do you agree? | C20: To what extent do you agree or disagree | D20: Education
A21: 17 | B21: Many education systems assess students' learning using formal written examinations. Those kinds of exams are a valid method. To what extent do you agree or disagree? Give examples with your own experience. | C21: To what extent do you agree or disagree | D21: Education
A22: 18 | B22: 'In a war of ideas, it is people who get killed'. Does a common man suffer from a group’s ideology? Express your opinion and support the same with reasons and examples. | C22: To what extent do you agree or disagree | D22: Socio-cultural and global issues | E22: Ethics | F22: Government, politics, and diplomacy
A23: 19 | B23: In many countries, the birth rates are lowering, and the problems of an ageing population are serious. What are the causes and the effects of this phenomenon? what should we do to address these issues? | C23: causes-problems-solutions | D23: Population | E23: Age, generation, and gender
A24: 20 | B24: In some countries around the world, voting is compulsory. Do you agree with the notion of compulsory voting? | C24: To what extent do you agree or disagree | D24: Government, politics, and diplomacy
A25: 21 | B25: In the 18th century due to industrialization, a lot of people migrated to developed countries. This affected lifestyle and increased problems in developed countries. What is your opinion about this? | C25: To what extent do you agree or disagree | D25: Population
A26: 22 | B26: In the past 100 years, there have been many inventions such as antibiotics, airplanes and computers. What do you think is the most important one? Why? | C26: To what extent do you agree or disagree | D26: Science, technology, and innovation
A27: 23 | B27: In your opinion, what are the advantages and disadvantages of extreme or adventure sports? | C27: Do the advantages outweigh the disadvantages | D27: Leisure, sports, and hobbies
A28: 24 | B28: The information revolution brought about by modern mass communications has both positive and negative consequences for individuals and society. To what extent do you agree with this statement? Give the reason with your own experience. | C28: To what extent do you agree or disagree | D28: Media and communication
A29: 25 | B29: Is a competitive environment in school or university good or bad? Discuss and give your own experiences as examples. | C29: others | D29: Education | E29: Leisure, sports, and hobbies
A30: 26 | B30: Is education as important to learn life values and ethics as to learn practical skills for future development? | C30: To what extent do you agree or disagree | D30: Education
A31: 27 | B31: It is argued that getting married before finishing studying or getting established in a good job is foolish. To what extent do you agree or disagree? | C31: To what extent do you agree or disagree | D31: Socio-cultural and global issues | E31: Work | F31: Education
A32: 28 | B32: It is important to preserve the beautiful buildings of the past, even if it will be expensive to do so. To what extent do you agree or disagree with it. | C32: To what extent do you agree or disagree | D32: Art and museums
A33: 29 | B33: In our technological world, the number of new inventions has been increasing. Please make an example with its impact on our life, and explain if it is beneficial or detrimental. | C33: others | D33: Science, technology, and innovation
A34: 30 | B34: In many towns and cities large shopping malls are replacing small local shops. Do you think this is a positive development? Give your reasons and examples. | C34: To what extent do you agree or disagree | D34: Economy, money, and trade | E34: Lifestyle | F34: City development
A35: 31 | B35: Learning a new language at an early age is helpful for children. It is more positive for their future prospects, though it can also have some adverse effects. Do you agree or disagree? | C35: To what extent do you agree or disagree | D35: Education | E35: Language | F35: Age, generation, and gender
A36: 32 | B36: Many people are living in poor lifestyles which affect their health. List some unhealthy lifestyles and give some solution suggestions to the national health service. | C36: others | D36: Food and health | E36: Lifestyle
A37: 33 | B37: Many people choose to emigrate to other countries. What are the advantages and disadvantages of living in a foreign country? Discuss with your own experience. | C37: Do the advantages outweigh the disadvantages | D37: Socio-cultural and global issues
A38: 34 | B38: Many workers like nurses and teachers should get more pay, especially in recent years when people in finance，film actors and company leaders are paid a larger amount of money. To what extent do you agree or disagree with the above statement and what’s your opinion? | C38: To what extent do you agree or disagree | D38: Economy, money, and trade | E38: Food and health | F38: Leisure, sports, and hobbies
A39: 35 | B39: The mass media, such as TV, radio and newspapers, have an influence on people, particularly on younger generations. It plays a pivotal role in shaping the opinions of people, especially teenagers and young people. To what extent do you agree with this? Please give examples. | C39: To what extent do you agree or disagree | D39: Media and communication | E39: Age, generation, and gender
A40: 36 | B40: Most high-level jobs are done by men. Should governments reserve a certain percentage of these jobs for women? | C40: To what extent do you agree or disagree | D40: Age, generation, and gender | E40: Government, politics, and diplomacy | F40: Work
A41: 37 | B41: Now doctors can talk to patients by using internet-based communication in the office. Discuss the advantages and disadvantages. | C41: Do the advantages outweigh the disadvantages | D41: Science, technology, and innovation
A42: 38 | B42: Nowadays television has become an essential part of life. It is a medium for disseminating news and information, and for some it acts as a companion. What is your opinion about this? | C42: To what extent do you agree or disagree | D42: Media and communication
A43: 39 | B43: Nowadays, it is increasingly more difficult to maintain the right balance between work and the other aspects of one’s life, such as leisure pursuits with family members. How important do you think this balance is? What are the reasons that make some people think that this is hard to achieve？ | C43: others | D43: Work | E43: Lifestyle
A44: 40 | B44: Many people find that work leaves little time for people's personal life. How widespread do you think it is? How can we solve the problems caused by the shortage of time? | C44: causes-problems-solutions | D44: Work
A45: 41 | B45: Online materials like music, movies and other forms of content are accessible at no cost. Do you think online materials should be accessed at no cost? | C45: To what extent do you agree or disagree | D45: Media and communication
A46: 42 | B46: Over half of population lives in cities. Is it a positive or negative development? | C46: Is it a positive or negative development | D46: City development | E46: Population
A47: 43 | B47: Should parents be held legally responsible for the actions of their children? Support your opinion from your study, observations or experiences. | C47: others | D47: Crime, punishment, and law | E47: Age, generation, and gender | F47: Ethics
A48: 44 | B48: People are moving from rural areas to big cities. Is it good or bad? | C48: others | D48: Population | E48: Government, politics, and diplomacy | F48: Economy, money, and trade
A49: 45 | B49: Pop music should have a university degree. Do you agree or disagree? | C49: To what extent do you agree or disagree | D49: Art and museums | E49: Education
A50: 46 | B50: In some companies, employers involve workers in the decision-making process about products and services. What are the advantages and disadvantages of such a policy? | C50: Do the advantages outweigh the disadvantages | D50: Work
A51: 47 | B51: Should individuals limit the use of cars and use alternatives instead to protect the environment? | C51: To what extent do you agree or disagree | D51: Environment | E51: Traffic
A52: 48 | B52: Should marketing for consumer goods companies like clothing and food place emphasis on reputation or short-term strategies like discounts and special offers? | C52: others | D52: Economy, money, and trade
A53: 49 | B53: In the company, some people think the employers should involve the workers in decision making. Discuss the advantages and disadvantages. | C53: Do the advantages outweigh the disadvantages | D53: Work
A54: 50 | B54: Some effective people live in a repetitive routine, such as eating the same food. Do you enjoy this lifestyle? | C54: To what extent do you agree or disagree | D54: Lifestyle
A55: 51 | B55: With the development of technology and science, some people believe that there is no great value of artists such as musicians and painters. What are the things artists can do but the scientist cannot? Why should we encourage studying in art area? | C55: To what extent do you agree or disagree | D55: Socio-cultural and global issues | E55: Education | F55: Art and museums
A56: 52 | B56: Some people believe that the sole aim of higher education is to make people ready for employment. To what extent do you agree or disagree? Discuss. | C56: To what extent do you agree or disagree | D56: Education
A57: 53 | B57: Some people claim that the digital age has made us lazier, while others claim it has made us more knowledgeable. Discuss both opinions, and use examples to support them. | C57: Discuss both views and give your opinions | D57: Science, technology, and innovation
A58: 54 | B58: Some people claim that instead of having to prepare for huge numbers of exams in school, children should learn more. To what extent do you agree with this statement? | C58: To what extent do you agree or disagree | D58: Education
A59: 56 | B59: Some people point that experiential learning (i.e. learning by doing it) can work well in formal education. However, others think a traditional form of teaching is the best. Do you think experiential learning can work well in high schools or colleges? | C59: To what extent do you agree or disagree | D59: Education
A60: 57 | B60: Some people said creativity is something a person was born with. Others thought creativity can be taught and developed. What’s your opinion? Explain. | C60: others | D60: Education
A61: 58 | B61: What is the role of writing theater plays and discussing historical writings in the study of high school students? | C61: others | D61: Education
A62: 59 | B62: Some people think placing advertisements in school is a great resource for public schools that need additional funding, but others think it exploits children by treating them as a captive audience for corporate sponsors. Choose which position you most agree with and discuss why you choose that position. Support your point of view with details from your own experiences, observations or reading. | C62: To what extent do you agree or disagree | D62: Ethics | E62: Education | F62: Media and communication
A63: 60 | B63: Some people think schools should group students according to their academic abilities while others think students can achieve better performance in mixed groups. Discuss both opinions and give your own opinion. | C63: Discuss both views and give your opinions | D63: Education
A64: 61 | B64: Some people think the law changes our behavior. Do you agree or disagree? | C64: To what extent do you agree or disagree | D64: Crime, punishment, and law
A65: 62 | B65: Some schools schedule all the exams at the end of each year, while other schools schedule them throughout the whole year. What are the advantages and disadvantages of these two strategies? Which one do you think is better? | C65: Do the advantages outweigh the disadvantages | D65: Education
A66: 63 | B66: Some universities deduct marks from students' work if it is handed in late. What is your opinion? What other actions do you recommend? | C66: To what extent do you agree or disagree | D66: Education
A67: 64 | B67: Space travel is fantastic these days, but there are many issues – such as environmental problems – that we should be focusing on. What are your views on the allocation of public funding to space travel? | C67: To what extent do you agree or disagree | D67: Science, technology, and innovation
A68: 65 | B68: Sports and games create disturbance in students’ life because students cannot fully concentrate on their studies. To what extent do you agree or disagree? | C68: To what extent do you agree or disagree | D68: Education | E68: Leisure, sports, and hobbies | F68: Food and health
A69: 66 | B69: Students can obtain information of academic subjects from online, the printed books and articles, and discussion with their teachers and their peers. Which one is the most reliable source? | C69: others | D69: Education
A70: 67 | B70: Some say that in today’s world the value of humanities has been eclipsed by the necessity of preparing for specific wealth-producing careers, such as medicine. What is your opinion about a role in today’s changing world for study of the humanities? | C70: To what extent do you agree or disagree | D70: Education
A71: 68 | B71: Successful sports stars and glamorous film stars act as role models for youngsters. Do you support this or not? | C71: To what extent do you agree or disagree | D71: Leisure, sports, and hobbies
A72: 69 | B72: Talk about an invention that you think beneficial or harmful. | C72: others | D72: Science, technology, and innovation
A73: 70 | B73: Teenagers should receive lessons on principles of personal finance, such as investing and debt. To what extent do you agree with this statement? | C73: To what extent do you agree or disagree | D73: Education
A74: 71 | B74: Medical technology is responsible for increasing the average life expectancy. Do you think it is a curse or a blessing? | C74: To what extent do you agree or disagree | D74: Science, technology, and innovation
A75: 72 | B75: Do you think the design of buildings affects, positively or negatively, where people live and work? | C75: others | D75: City development
A76: 73 | B76: Animal rights have been a subject of debate since the 1970s. Are zoos helping or hurting animals? | C76: others | D76: Animals | E76: Ethics
A77: 74 | B77: The purpose of education is for workers and good members of society, or individuals to fulfill their life. Which opinion do you agree with? | C77: To what extent do you agree or disagree | D77: Education | E77: Work | F77: Socio-cultural and global issues
A78: 75 | B78: Nowadays, people who devote too much time to their job leave very little time for their personal and private life. How widespread is the problem? What problem will this shortage of time cause? | C78: others | D78: Work
A79: 76 | B79: The world's governments and international organizations confront a multitude of global problems. Which do you think is the most pressing problem for the inhabitants of our planet and give the solution? | C79: others | D79: Socio-cultural and global issues
A80: 77 | B80: What are the problems and the benefits for high school students of studying plays and other works for theatre that were written centuries ago? Do you agree with it? Use your own experience to discuss it. | C80: To what extent do you agree or disagree | D80: Education | E80: Art and museums
A81: 78 | B81: There is no need for newspapers in the modern world. To what extent do you agree or disagree? | C81: To what extent do you agree or disagree | D81: Media and communication | E81: Science, technology, and innovation
A82: 79 | B82: Tourism is good for a less developed country, but disadvantages of tourism can be as great as advantages. Discuss it. | C82: others | D82: Travelling and tourism
A83: 80 | B83: We have entered a throw-away society and have filled the environment with rubbish. What are the causes and what are your solutions? | C83: causes-problems-solutions | D83: Environment
A84: 81 | B84: What are the advantages and disadvantages for students doing part-time jobs? | C84: Do the advantages outweigh the disadvantages | D84: Education
A85: 82 | B85: What are the advantages and disadvantages of living in an era in which new things are constantly being invented? | C85: Do the advantages outweigh the disadvantages | D85: Science, technology, and innovation
A86: 83 | B86: What are the pros and cons of staying connected on social media 24 hours a day? | C86: others | D86: Media and communication
A87: 84 | B87: What is your view on the idea that it takes failure to achieve success? | C87: To what extent do you agree or disagree | D87: Education | E87: Ethics | F87: Work
A88: 85 | B88: With enough amount of motivation and practice, people can learn anything that the experts teach in the classroom. Do you agree or not? | C88: To what extent do you agree or disagree | D88: Education
A89: 86 | B89: With the increase of digital media available online, the role of the library has become obsolete. Universities should only procure new digital media rather than constantly update textbooks. Discuss both the advantages and disadvantages of this position and give your own point of view. | C89: Do the advantages outweigh the disadvantages | D89: Education
A90: 87 | B90: Xenophobia has accelerated rapidly in the western countries. According to you what solutions can be proposed by government and individuals? | C90: others | D90: Socio-cultural and global issues
A91: 88 | B91: Many people say there is much violence promoted in mass media. What is your opinion? | C91: To what extent do you agree or disagree | D91: Media and communication
A92: 89 | B92: Rather than choose a subject that is suitable for future employment possibilities, you should choose a subject that you interested in or could get good grades. Agree or disagree? | C92: To what extent do you agree or disagree | D92: Education
A93: 90 | B93: Age restrictions are placed on many activities. It is believed that people should not do things until they reach the right ages, such as getting married, driving, voting, buying certain products, and doing particular things. Give an example, state which minimum age you think it should be and share your own experience. | C93: others | D93: Age, generation, and gender
A94: 91 | B94: The issue of overcrowding is addressed by city planners, not the policy-making population. What is your opinion about this statement? | C94: To what extent do you agree or disagree | D94: City development | E94: Population
A95: 92 | B95: A good listener is better than a good talker in a social situation. Do you agree or disagree? | C95: To what extent do you agree or disagree | D95: Media and communication
A96: 93 | B96: Being a journalist is one of the most difficult jobs in the world. To what extent, you agree with it? | C96: To what extent do you agree or disagree | D96: Media and communication
A97: 94 | B97: "National happiness index" has better performance than economic increase in a nation’s development. Do you agree and how to measure "national happiness"? | C97: To what extent do you agree or disagree | D97: Socio-cultural and global issues
A98: 95 | B98: In a cashless society, people in more and more situations use credit cards instead of cash. Cashless society seems to be a reality. How realistic do you think it might be? What are the potential benefits or problems of this phenomenon? | C98: others | D98: Economy, money, and trade
A99: 96 | B99: Some people think air travel has more negative impacts than positive impacts on modern life. What do you think? | C99: others | D99: Environment | E99: Lifestyle | F99: Science, technology, and innovation
A100: 97 | B100: Experience is more effective and useful than books and formal education. To what extent do you agree with this opinion? | C100: To what extent do you agree or disagree | D100: Education
A101: 98 | B101: Global problems are related to governments and international organizations. What are the problems and what is your solution? | C101: others | D101: Government, politics, and diplomacy
...

Sheet Topic Statistics
A1: Topic Statistics – Weighted Primary/Secondary Model | J1: Model inputs
A2: Primary topic weight = 1.0; each secondary topic weight = 0.5. Weighted score = Primary count + 0.5 × Secondary count. | J2: Primary-topic weight | K2: 1
J3: Secondary-topic weight | K3: 0.5
A4: Rank | B4: Topic | C4: Primary count | D4: Secondary count | E4: Weighted score | F4: Weighted share | G4: Raw coverage count | H4: Raw coverage % | J4: Number of prompts | K4: 453
A5: 1 | B5: Education | C5: =COUNTIF('453 Prompts'!$D$5:$D$457, B5) | D5: =COUNTIF('453 Prompts'!$E$5:$E$457, B5) + COUNTIF('453 Prompts'!$F$5:$F$457, B5) | E5: =C5*$K$2 + D5*$K$3 | F5: =E5/$E$27 | G5: =C5+D5 | H5: =G5/$K$4
A6: 2 | B6: Socio-cultural and global issues | C6: =COUNTIF('453 Prompts'!$D$5:$D$457, B6) | D6: =COUNTIF('453 Prompts'!$E$5:$E$457, B6) + COUNTIF('453 Prompts'!$F$5:$F$457, B6) | E6: =C6*$K$2 + D6*$K$3 | F6: =E6/$E$27 | G6: =C6+D6 | H6: =G6/$K$4 | J6: Key results
A7: 3 | B7: Science, technology, and innovation | C7: =COUNTIF('453 Prompts'!$D$5:$D$457, B7) | D7: =COUNTIF('453 Prompts'!$E$5:$E$457, B7) + COUNTIF('453 Prompts'!$F$5:$F$457, B7) | E7: =C7*$K$2 + D7*$K$3 | F7: =E7/$E$27 | G7: =C7+D7 | H7: =G7/$K$4 | J7: Primary assignments | K7: =C27
A8: 4 | B8: Media and communication | C8: =COUNTIF('453 Prompts'!$D$5:$D$457, B8) | D8: =COUNTIF('453 Prompts'!$E$5:$E$457, B8) + COUNTIF('453 Prompts'!$F$5:$F$457, B8) | E8: =C8*$K$2 + D8*$K$3 | F8: =E8/$E$27 | G8: =C8+D8 | H8: =G8/$K$4 | J8: Secondary assignments | K8: =D27
A9: 5 | B9: Lifestyle | C9: =COUNTIF('453 Prompts'!$D$5:$D$457, B9) | D9: =COUNTIF('453 Prompts'!$E$5:$E$457, B9) + COUNTIF('453 Prompts'!$F$5:$F$457, B9) | E9: =C9*$K$2 + D9*$K$3 | F9: =E9/$E$27 | G9: =C9+D9 | H9: =G9/$K$4 | J9: Total weighted score | K9: =E27
A10: 6 | B10: Work | C10: =COUNTIF('453 Prompts'!$D$5:$D$457, B10) | D10: =COUNTIF('453 Prompts'!$E$5:$E$457, B10) + COUNTIF('453 Prompts'!$F$5:$F$457, B10) | E10: =C10*$K$2 + D10*$K$3 | F10: =E10/$E$27 | G10: =C10+D10 | H10: =G10/$K$4 | J10: Average topics per prompt | K10: =(C27+D27)/K4
A11: 7 | B11: Environment | C11: =COUNTIF('453 Prompts'!$D$5:$D$457, B11) | D11: =COUNTIF('453 Prompts'!$E$5:$E$457, B11) + COUNTIF('453 Prompts'!$F$5:$F$457, B11) | E11: =C11*$K$2 + D11*$K$3 | F11: =E11/$E$27 | G11: =C11+D11 | H11: =G11/$K$4 | J11: Average weighted units per prompt | K11: =E27/K4
A12: 8 | B12: Economy, money, and trade | C12: =COUNTIF('453 Prompts'!$D$5:$D$457, B12) | D12: =COUNTIF('453 Prompts'!$E$5:$E$457, B12) + COUNTIF('453 Prompts'!$F$5:$F$457, B12) | E12: =C12*$K$2 + D12*$K$3 | F12: =E12/$E$27 | G12: =C12+D12 | H12: =G12/$K$4
A13: 9 | B13: Age, generation, and gender | C13: =COUNTIF('453 Prompts'!$D$5:$D$457, B13) | D13: =COUNTIF('453 Prompts'!$E$5:$E$457, B13) + COUNTIF('453 Prompts'!$F$5:$F$457, B13) | E13: =C13*$K$2 + D13*$K$3 | F13: =E13/$E$27 | G13: =C13+D13 | H13: =G13/$K$4
A14: 10 | B14: Food and health | C14: =COUNTIF('453 Prompts'!$D$5:$D$457, B14) | D14: =COUNTIF('453 Prompts'!$E$5:$E$457, B14) + COUNTIF('453 Prompts'!$F$5:$F$457, B14) | E14: =C14*$K$2 + D14*$K$3 | F14: =E14/$E$27 | G14: =C14+D14 | H14: =G14/$K$4
A15: 11 | B15: Leisure, sports, and hobbies | C15: =COUNTIF('453 Prompts'!$D$5:$D$457, B15) | D15: =COUNTIF('453 Prompts'!$E$5:$E$457, B15) + COUNTIF('453 Prompts'!$F$5:$F$457, B15) | E15: =C15*$K$2 + D15*$K$3 | F15: =E15/$E$27 | G15: =C15+D15 | H15: =G15/$K$4
A16: 12 | B16: City development | C16: =COUNTIF('453 Prompts'!$D$5:$D$457, B16) | D16: =COUNTIF('453 Prompts'!$E$5:$E$457, B16) + COUNTIF('453 Prompts'!$F$5:$F$457, B16) | E16: =C16*$K$2 + D16*$K$3 | F16: =E16/$E$27 | G16: =C16+D16 | H16: =G16/$K$4
A17: 13 | B17: Ethics | C17: =COUNTIF('453 Prompts'!$D$5:$D$457, B17) | D17: =COUNTIF('453 Prompts'!$E$5:$E$457, B17) + COUNTIF('453 Prompts'!$F$5:$F$457, B17) | E17: =C17*$K$2 + D17*$K$3 | F17: =E17/$E$27 | G17: =C17+D17 | H17: =G17/$K$4
A18: 14 | B18: Government, politics, and diplomacy | C18: =COUNTIF('453 Prompts'!$D$5:$D$457, B18) | D18: =COUNTIF('453 Prompts'!$E$5:$E$457, B18) + COUNTIF('453 Prompts'!$F$5:$F$457, B18) | E18: =C18*$K$2 + D18*$K$3 | F18: =E18/$E$27 | G18: =C18+D18 | H18: =G18/$K$4
A19: 15 | B19: Population | C19: =COUNTIF('453 Prompts'!$D$5:$D$457, B19) | D19: =COUNTIF('453 Prompts'!$E$5:$E$457, B19) + COUNTIF('453 Prompts'!$F$5:$F$457, B19) | E19: =C19*$K$2 + D19*$K$3 | F19: =E19/$E$27 | G19: =C19+D19 | H19: =G19/$K$4
A20: 16 | B20: Crime, punishment, and law | C20: =COUNTIF('453 Prompts'!$D$5:$D$457, B20) | D20: =COUNTIF('453 Prompts'!$E$5:$E$457, B20) + COUNTIF('453 Prompts'!$F$5:$F$457, B20) | E20: =C20*$K$2 + D20*$K$3 | F20: =E20/$E$27 | G20: =C20+D20 | H20: =G20/$K$4
A21: 17 | B21: Travelling and tourism | C21: =COUNTIF('453 Prompts'!$D$5:$D$457, B21) | D21: =COUNTIF('453 Prompts'!$E$5:$E$457, B21) + COUNTIF('453 Prompts'!$F$5:$F$457, B21) | E21: =C21*$K$2 + D21*$K$3 | F21: =E21/$E$27 | G21: =C21+D21 | H21: =G21/$K$4
A22: 18 | B22: Climate | C22: =COUNTIF('453 Prompts'!$D$5:$D$457, B22) | D22: =COUNTIF('453 Prompts'!$E$5:$E$457, B22) + COUNTIF('453 Prompts'!$F$5:$F$457, B22) | E22: =C22*$K$2 + D22*$K$3 | F22: =E22/$E$27 | G22: =C22+D22 | H22: =G22/$K$4
A23: 19 | B23: Language | C23: =COUNTIF('453 Prompts'!$D$5:$D$457, B23) | D23: =COUNTIF('453 Prompts'!$E$5:$E$457, B23) + COUNTIF('453 Prompts'!$F$5:$F$457, B23) | E23: =C23*$K$2 + D23*$K$3 | F23: =E23/$E$27 | G23: =C23+D23 | H23: =G23/$K$4
... A26: 22 | B26: Traffic | C26: =COUNTIF('453 Prompts'!$D$5:$D$457, B26) | D26: =COUNTIF('453 Prompts'!$E$5:$E$457, B26) + COUNTIF('453 Prompts'!$F$5:$F$457, B26) | E26: =C26*$K$2 + D26*$K$3 | F26: =E26/$E$27 | G26: =C26+D26 | H26: =G26/$K$4
A27: Total | C27: =SUM(C5:C26) | D27: =SUM(D5:D26) | E27: =SUM(E5:E26) | F27: =SUM(F5:F26) | G27: =SUM(G5:G26) | H27: =E27/$K$4

Sheet Task Type Statistics
A1: Task Type Statistics – Single-Label Classification
A2: Each of the 453 prompts is assigned to exactly one task type.
A4: Rank | B4: Task type | C4: Count | D4: Percentage
A5: 1 | B5: To what extent do you agree or disagree | C5: =COUNTIF('453 Prompts'!$C$5:$C$457, B5) | D5: =C5/$C$11
A6: 2 | B6: others | C6: =COUNTIF('453 Prompts'!$C$5:$C$457, B6) | D6: =C6/$C$11
A7: 3 | B7: Do the advantages outweigh the disadvantages | C7: =COUNTIF('453 Prompts'!$C$5:$C$457, B7) | D7: =C7/$C$11
A8: 4 | B8: Is it a positive or negative development | C8: =COUNTIF('453 Prompts'!$C$5:$C$457, B8) | D8: =C8/$C$11
A9: 5 | B9: causes-problems-solutions | C9: =COUNTIF('453 Prompts'!$C$5:$C$457, B9) | D9: =C9/$C$11
A10: 6 | B10: Discuss both views and give your opinions | C10: =COUNTIF('453 Prompts'!$C$5:$C$457, B10) | D10: =C10/$C$11
A11: Total | C11: =SUM(C5:C10) | D11: =SUM(D5:D10)
